Metadata-Version: 2.1
Name: dio-image-processing
Version: 0.0.1
Summary: Image processing package in Python using the Skimage package
Home-page: https://github.com/hadirga/dio-create-an-image-processing-package
Author: Hadir Garcia
Requires-Python: >=3.7
Requires-Dist: numpy
Requires-Dist: matplotlib
Requires-Dist: scikit-image (>=0.19.3)
